LICENSE
MANIFEST.in
README.rst
setup.py
chembl_migrate/__init__.py
chembl_migrate/models.py
chembl_migrate/tests.py
chembl_migrate.egg-info/PKG-INFO
chembl_migrate.egg-info/SOURCES.txt
chembl_migrate.egg-info/dependency_links.txt
chembl_migrate.egg-info/not-zip-safe
chembl_migrate.egg-info/requires.txt
chembl_migrate.egg-info/top_level.txt
chembl_migrate/management/__init__.py
chembl_migrate/management/commands/__init__.py
chembl_migrate/management/commands/execute_sql_custom.py
chembl_migrate/management/commands/migrate.py
chembl_migrate/management/commands/migrate_table.py
chembl_migrate/management/commands/reverseEngineer.py